TheLinuxCommandLineZhongwenban/README.md
TheLinuxCommandLineZhongwenban/__init__.py
TheLinuxCommandLineZhongwenban/__main__.py
TheLinuxCommandLineZhongwenban/file.epub
TheLinuxCommandLineZhongwenban/index.html
TheLinuxCommandLineZhongwenban/css/__init__.py
TheLinuxCommandLineZhongwenban/css/annotations.css
TheLinuxCommandLineZhongwenban/css/main.css
TheLinuxCommandLineZhongwenban/css/normalize.css
TheLinuxCommandLineZhongwenban/css/popup.css
TheLinuxCommandLineZhongwenban/font/__init__.py
TheLinuxCommandLineZhongwenban/font/fontello.eot
TheLinuxCommandLineZhongwenban/font/fontello.svg
TheLinuxCommandLineZhongwenban/font/fontello.ttf
TheLinuxCommandLineZhongwenban/font/fontello.woff
TheLinuxCommandLineZhongwenban/img/__init__.py
TheLinuxCommandLineZhongwenban/img/annotator-glyph-sprite.png
TheLinuxCommandLineZhongwenban/img/annotator-icon-sprite.png
TheLinuxCommandLineZhongwenban/img/apple-touch-icon.png
TheLinuxCommandLineZhongwenban/img/cancelfullscreen.png
TheLinuxCommandLineZhongwenban/img/close.png
TheLinuxCommandLineZhongwenban/img/fullscreen.png
TheLinuxCommandLineZhongwenban/img/loader.gif
TheLinuxCommandLineZhongwenban/img/menu-icon.png
TheLinuxCommandLineZhongwenban/img/save.png
TheLinuxCommandLineZhongwenban/img/saved.png
TheLinuxCommandLineZhongwenban/img/settings-s.png
TheLinuxCommandLineZhongwenban/img/settings.png
TheLinuxCommandLineZhongwenban/img/star.png
TheLinuxCommandLineZhongwenban/js/__init__.py
TheLinuxCommandLineZhongwenban/js/epub.js
TheLinuxCommandLineZhongwenban/js/epub.min.js
TheLinuxCommandLineZhongwenban/js/epub.min.map
TheLinuxCommandLineZhongwenban/js/hooks.min.js
TheLinuxCommandLineZhongwenban/js/hooks.min.map
TheLinuxCommandLineZhongwenban/js/reader.js
TheLinuxCommandLineZhongwenban/js/reader.js.map
TheLinuxCommandLineZhongwenban/js/reader.min.js
TheLinuxCommandLineZhongwenban/js/reader.min.map
TheLinuxCommandLineZhongwenban/js/hooks/__init__.py
TheLinuxCommandLineZhongwenban/js/hooks/extensions/__init__.py
the_linux_command_line_zhongwenban-2024.3.2.0.dist-info/METADATA
the_linux_command_line_zhongwenban-2024.3.2.0.dist-info/WHEEL
the_linux_command_line_zhongwenban-2024.3.2.0.dist-info/entry_points.txt
the_linux_command_line_zhongwenban-2024.3.2.0.dist-info/top_level.txt
the_linux_command_line_zhongwenban-2024.3.2.0.dist-info/RECORD
